mathslib/__init__.py
mathslib/algorithms.py
mathslib/divisors.py
mathslib/fib.py
mathslib/linalg.py
mathslib/numtheory.py
mathslib/primes.py
mathslib/simple.py
mathslib-3.2.0.dist-info/LICENSE.txt
mathslib-3.2.0.dist-info/METADATA
mathslib-3.2.0.dist-info/WHEEL
mathslib-3.2.0.dist-info/entry_points.txt
mathslib-3.2.0.dist-info/top_level.txt
mathslib-3.2.0.dist-info/RECORD
