Metadata-Version: 2.2
Name: mathslib
Version: 3.2.0
Summary: Library of Mathematical functions and Algorithms
Home-page: https://github.com/igorvanloo/mathslib
Author: Igor van Loo
Author-email: igorvanloo@gmail.com
Project-URL: Bug Reports, https://github.com/igorvanloo/mathslib/issues
Project-URL: Source, https://github.com/igorvanloo/mathslib
Keywords: numbertheory,maths,algorithms
Classifier: Development Status :: 3 - Alpha
Classifier: Natural Language :: English
Classifier: Programming Language :: Python :: 3
Classifier: Programming Language :: Python :: 3.6
Classifier: Programming Language :: Python :: 3.7
Classifier: Programming Language :: Python :: 3.8
Classifier: Programming Language :: Python :: 3.9
Requires-Python: >=3.7, <4
License-File: LICENSE.txt
Dynamic: author
Dynamic: author-email
Dynamic: classifier
Dynamic: description
Dynamic: description-content-type
Dynamic: home-page
Dynamic: keywords
Dynamic: project-url
Dynamic: requires-python
Dynamic: summary
